codon_sdk/agents/__init__.py
codon_sdk/agents/codon_workload.py
codon_sdk/agents/workload.py
codon_sdk/instrumentation/__init__.py
codon_sdk/instrumentation/config.py
codon_sdk/instrumentation/telemetry.py
codon_sdk/instrumentation/schemas/__init__.py
codon_sdk/instrumentation/schemas/logic_id/__init__.py
codon_sdk/instrumentation/schemas/logic_id/version.py
codon_sdk/instrumentation/schemas/nodespec/__init__.py
codon_sdk/instrumentation/schemas/nodespec/version.py
codon_sdk/instrumentation/schemas/telemetry/spans/__init__.py
codon_sdk/llm/__init__.py
codon_sdk-0.1.0a5.dist-info/licenses/LICENSE
codon_sdk-0.1.0a5.dist-info/METADATA
codon_sdk-0.1.0a5.dist-info/WHEEL
codon_sdk-0.1.0a5.dist-info/top_level.txt
codon_sdk-0.1.0a5.dist-info/RECORD
