Metadata-Version: 2.4
Name: codon_sdk
Version: 0.1.0a5
Summary: The core SDK for Codon project components, including agents and data schemas.
Author-email: "Codon, Inc." <martin@codonops.ai>, Martin Arroyo <martin@codonops.ai>, Sheldon Gilbert <sheldon@codonops.ai>
Maintainer-email: Martin Arroyo <martin@codonops.ai>, Carl Gordon <carl@codonops.ai>, Luis Moreno <luis@codonops.ai>
License: Apache-2.0
Project-URL: Homepage, https://github.com/Codon-Ops/codon-sdk
Project-URL: Bug Tracker, https://github.com/Codon-Ops/codon-sdk/issues
Project-URL: Documentation, https://codon-ops.github.io/codon-sdk/
Classifier: Programming Language :: Python :: 3
Classifier: Development Status :: 3 - Alpha
Classifier: Operating System :: OS Independent
Requires-Python: >=3.9
License-File: LICENSE
Requires-Dist: opentelemetry-api
Requires-Dist: opentelemetry-exporter-otlp-proto-grpc
Requires-Dist: opentelemetry-sdk
Requires-Dist: pydantic
Dynamic: license-file
